CHANGES.md
LICENSE
MANIFEST.in
README
README.md
setup.py
bin/process_rixs
bin/process_xes
bin/run_calibrate
bin/run_calibrate.bat
bin/run_evaluator.bat
bin/setup_rixs.bat
minixes2.egg-info/PKG-INFO
minixes2.egg-info/SOURCES.txt
minixes2.egg-info/dependency_links.txt
minixes2.egg-info/top_level.txt
minixs/__init__.py
minixs/calibrate.py
minixs/constants.py
minixs/dataset.py
minixs/emission.py
minixs/exposure.py
minixs/filetype.py
minixs/filter.py
minixs/gauss.py
minixs/geom.py
minixs/misc.py
minixs/parser.py
minixs/rixs.py
minixs/scanfile.py
minixs/spectrometer.py
minixs/config/__init__.py
minixs/config/minixsconfigparser.py
minixs/gui/__init__.py
minixs/gui/demo_image_view.py
minixs/gui/file_dialog.py
minixs/gui/filter_view.py
minixs/gui/frame.py
minixs/gui/image_tools.py
minixs/gui/image_view.py
minixs/gui/mouse_event.py
minixs/gui/util.py
minixs/gui/wildcards.py
minixs/gui/wxmpl.py
minixs/gui/calibrator/__init__.py
minixs/gui/calibrator/calibrator.py
minixs/gui/calibrator/calibrator_const.py
minixs/gui/calibrator/calibrator_controller.py
minixs/gui/calibrator/calibrator_view.py
minixs/gui/processor/__init__.py
minixs/gui/processor/const.py
minixs/gui/processor/controller.py
minixs/gui/processor/main.py
minixs/gui/processor/view.py
minixs/gui/qtcalibrator/ImageViewQt.py
minixs/gui/qtcalibrator/__init__.py
minixs/gui/qtcalibrator/__main__.py
minixs/gui/qtcalibrator/calibratorexposureselector.py
minixs/gui/qtcalibrator/calibratormain.py
minixs/gui/qtcalibrator/calibratormainwindow.py
minixs/gui/qtcalibrator/model/__init__.py
minixs/gui/qtcalibrator/model/exposurelistmodel.py
minixs/gui/qtcalibrator/view/__init__.py
minixs/gui/qtcalibrator/view/exposurelistview.py
minixs/gui/qtevaluator/__init__.py
minixs/gui/qtevaluator/__main__.py
minixs/gui/qtevaluator/evaluatorcontrols.py
minixs/gui/qtevaluator/evaluatormain.py
minixs/gui/qtevaluator/evaluatormainwindow.py
minixs/gui/qtevaluator/imageview.py
minixs/gui/qtevaluator/plotview.py
minixs/gui/qthelpers/__init__.py
minixs/gui/qthelpers/qtfilterview.py
minixs/gui/qthelpers/wildcards.py
test/__init__.py
test/grab_xtals.py
test/imageViewTest.py
